vtb_authorizer_utils/__init__.py
vtb_authorizer_utils/authorizer_schema_builder.py
vtb_authorizer_utils/config.py
vtb_authorizer_utils/converters.py
vtb_authorizer_utils/data_objects.py
vtb_authorizer_utils/decorators.py
vtb_authorizer_utils/errors.py
vtb_authorizer_utils/gateway.py
vtb_authorizer_utils/utils.py
vtb_authorizer_utils-0.0.28.dist-info/METADATA
vtb_authorizer_utils-0.0.28.dist-info/WHEEL
vtb_authorizer_utils-0.0.28.dist-info/top_level.txt
vtb_authorizer_utils-0.0.28.dist-info/RECORD
