Metadata-Version: 2.1
Name: vtb-authorizer-utils
Version: 0.0.28
Summary: Утилитарный пакет, содержащий в себе интеграционный модуль с сервисом Authorizer. Детали смотри в README.md.
Author: VTB python team
Author-email: python.team@vtb.ru
License: UNKNOWN
Keywords: python,microservices,utils,http
Platform: UNKNOWN
Classifier: Programming Language :: Python :: 3.8
Classifier: Operating System :: OS Independent
Requires-Python: >=3.8
Requires-Dist: vtb-http-interaction
Requires-Dist: singleton3
Provides-Extra: test
Requires-Dist: pytest ; extra == 'test'
Requires-Dist: pytest-cov ; extra == 'test'
Requires-Dist: pytest-aiohttp ; extra == 'test'
Requires-Dist: pytest-mock ; extra == 'test'
Requires-Dist: pylint ; extra == 'test'
Requires-Dist: pytest-dotenv ; extra == 'test'
Requires-Dist: envparse ; extra == 'test'
